LICENSE
README.md
pyproject.toml
setup.cfg
setup.py
constant_contact_api_client/__init__.py
constant_contact_api_client/api_client.py
constant_contact_api_client/api_response.py
constant_contact_api_client/configuration.py
constant_contact_api_client/exceptions.py
constant_contact_api_client/py.typed
constant_contact_api_client/rest.py
constant_contact_api_client.egg-info/PKG-INFO
constant_contact_api_client.egg-info/SOURCES.txt
constant_contact_api_client.egg-info/dependency_links.txt
constant_contact_api_client.egg-info/requires.txt
constant_contact_api_client.egg-info/top_level.txt
constant_contact_api_client/api/__init__.py
constant_contact_api_client/api/account_services_api.py
constant_contact_api_client/api/bulk_activities_api.py
constant_contact_api_client/api/contact_lists_api.py
constant_contact_api_client/api/contact_tags_api.py
constant_contact_api_client/api/contacts_api.py
constant_contact_api_client/api/contacts_custom_fields_api.py
constant_contact_api_client/api/contacts_reporting_api.py
constant_contact_api_client/api/email_campaigns_ab_tests_api.py
constant_contact_api_client/api/email_campaigns_api.py
constant_contact_api_client/api/email_reporting_api.py
constant_contact_api_client/api/email_scheduling_api.py
constant_contact_api_client/api/landing_pages_reporting_api.py
constant_contact_api_client/api/segments_api.py
constant_contact_api_client/models/__init__.py
constant_contact_api_client/models/ab_test_data.py
constant_contact_api_client/models/access_token_response.py
constant_contact_api_client/models/account_cancellation.py
constant_contact_api_client/models/account_email_create_response.py
constant_contact_api_client/models/account_email_input.py
constant_contact_api_client/models/account_physical_address.py
constant_contact_api_client/models/account_suspension.py
constant_contact_api_client/models/activities.py
constant_contact_api_client/models/activity.py
constant_contact_api_client/models/activity_delete_custom_fields.py
constant_contact_api_client/models/activity_delete_list_response.py
constant_contact_api_client/models/activity_delete_lists_response.py
constant_contact_api_client/models/activity_delete_status.py
constant_contact_api_client/models/activity_errors.py
