Metadata-Version: 2.1
Name: constant-contact-api-client
Version: 1.1.0
Summary: Constant Contact API v3
Home-page: 
Author: Constant Contact Public API
Author-email: webservices@constantcontact.com
License: Private
Keywords: OpenAPI,OpenAPI-Generator,Constant Contact API v3
License-File: LICENSE
